ids_tk-1.2.1.dist-info/METADATA
ids_tk-1.2.1.dist-info/WHEEL
ids_tk/schemas/bef.json
ids_tk/schemas/lpr3_kontakter.json
ids_tk/schemas/uddf.json
ids_tk/schemas/lpr3_diagnoser.json
ids_tk/schemas/ind.json
ids_tk/schemas/lpr_adm.json
ids_tk/schemas/idan.json
ids_tk/schemas/lpr_bes.json
ids_tk/schemas/akm.json
ids_tk/schemas/lpr_diag.json
ids_tk/__init__.py
ids_tk/mappings/hustype.json
ids_tk/mappings/icd10.json
ids_tk/mappings/civst.json
ids_tk/mappings/fm_mark.json
ids_tk/mappings/beskst13.json
ids_tk/mappings/scd.json
ids_tk/mappings/socio13.json
ids_tk/mappings/family_type.json
ids_tk/mappings/plads.json
ids_tk/mappings/hfaudd.json
ids_tk/mappings/statsb.json
ids_tk/mappings/tilknyt.json
ids_tk/mappings/jobkat.json
ids_tk/mappings/pre_socio.json
ids_tk/mappings/reg.json
ids_tk-1.2.1.data/scripts/ids
ids_tk.libs/libbrotlicommon-a91ead09.so.1
ids_tk.libs/libbrotlidec-64d8a501.so.1
ids_tk.libs/libbz2-218c4abd.so.1.0
ids_tk.libs/libfontconfig-a94b4059.so.1
ids_tk.libs/libfreetype-fd0e5281.so.6
ids_tk.libs/libpng16-29896eea.so.16
ids_tk-1.2.1.dist-info/RECORD
